genta/__init__.py
genta/api.py
genta-0.0.3.12.dist-info/METADATA
genta-0.0.3.12.dist-info/WHEEL
genta-0.0.3.12.dist-info/licenses/LICENSE
genta-0.0.3.12.dist-info/RECORD
