Metadata-Version: 2.1
Name: genta
Version: 0.0.3.12
Summary: Simple python interface to access models from Genta API.
Project-URL: Homepage, https://github.com/Genta-Technology/genta-api
Project-URL: Bug Tracker, https://github.com/Genta-Technology/genta-api/issues
Author-email: Rifky Bujana Bisri <rifky@genta.tech>
License-File: LICENSE
Classifier: License :: OSI Approved :: MIT License
Classifier: Operating System :: OS Independent
Classifier: Programming Language :: Python :: 3
Requires-Python: >=3.7
